inequalitychay/__init__.py
inequalitychay/inequalitychay.py
inequalitychay-1.0.1.dist-info/LICENSE
inequalitychay-1.0.1.dist-info/METADATA
inequalitychay-1.0.1.dist-info/WHEEL
inequalitychay-1.0.1.dist-info/top_level.txt
inequalitychay-1.0.1.dist-info/RECORD
